specmaker_core/__init__.py
specmaker_core/init.py
specmaker_core/review.py
specmaker_core/_dependencies/__init__.py
specmaker_core/_dependencies/errors.py
specmaker_core/_dependencies/types.py
specmaker_core/_dependencies/config/__init__.py
specmaker_core/_dependencies/config/constants.py
specmaker_core/_dependencies/config/types.py
specmaker_core/_dependencies/logging/__init__.py
specmaker_core/_dependencies/logging/json_logger.py
specmaker_core/_dependencies/schemas/__init__.py
specmaker_core/_dependencies/schemas/documents.py
specmaker_core/_dependencies/schemas/events.py
specmaker_core/_dependencies/schemas/shared.py
specmaker_core/_dependencies/templates/__init__.py
specmaker_core/_dependencies/templates/architect.jinja2
specmaker_core/_dependencies/templates/readme.jinja2
specmaker_core/_dependencies/templates/reviewer.jinja2
specmaker_core/_dependencies/templates/writer.jinja2
specmaker_core/_dependencies/toolsets/__init__.py
specmaker_core/_dependencies/toolsets/common_tools.py
specmaker_core/_dependencies/toolsets/rag_tools.py
specmaker_core/_dependencies/toolsets/text_tools.py
specmaker_core/_dependencies/utils/__init__.py
specmaker_core/_dependencies/utils/handoff.py
specmaker_core/_dependencies/utils/paths.py
specmaker_core/_dependencies/utils/serialization.py
specmaker_core/agents/__init__.py
specmaker_core/agents/architect.py
specmaker_core/agents/reviewer.py
specmaker_core/agents/writer.py
specmaker_core/config/__init__.py
specmaker_core/config/settings.py
specmaker_core/contracts/__init__.py
specmaker_core/durable/__init__.py
specmaker_core/durable/dbos_boot.py
specmaker_core/durable/review_flow.py
specmaker_core/durable/steps.py
specmaker_core/evals/__init__.py
specmaker_core/evals/datasets.py
specmaker_core/evals/evaluators.py
specmaker_core/logging/__init__.py
specmaker_core/logging/log.py
specmaker_core/persistence/__init__.py
specmaker_core/persistence/metadata.py
specmaker_core/persistence/models.py
specmaker_core/persistence/storage.py
specmaker-0.0.1.dist-info/METADATA
specmaker-0.0.1.dist-info/WHEEL
specmaker-0.0.1.dist-info/RECORD
