Metadata-Version: 2.4
Name: specmaker
Version: 0.0.1
Summary: SpecMaker is an Multi-Agent documentation system that guides engineers through structured, human-in-the-loop flows to produce high-quality, consistent, and AI-readable specs.
Author-email: Darec Stowell <darec.specmaker@gmail.com>
Requires-Python: >=3.13
Requires-Dist: jinja2>=3.1.6
Requires-Dist: pydantic-ai[dbos]>=0.0.17
Requires-Dist: pydantic-settings>=2.11.0
Requires-Dist: pydantic>=2.9.2
Requires-Dist: sqlalchemy>=2.0.44
